Metadata-Version: 1.0
Name: distribut
Version: 0.1
Summary: Gaussian distributions
Home-page: UNKNOWN
Author: Trav
Author-email: nduas77@gmail.com
License: UNKNOWN
Platform: UNKNOWN
